spotify_youtube_migrator/__init__.py
spotify_youtube_migrator/cli.py
spotify_youtube_migrator/config.py
spotify_youtube_migrator/spotify.py
spotify_youtube_migrator/utils.py
spotify_youtube_migrator/youtube.py
spotify_youtube_migrator-2.0.0.dist-info/licenses/LICENSE
spotify_youtube_migrator-2.0.0.dist-info/METADATA
spotify_youtube_migrator-2.0.0.dist-info/WHEEL
spotify_youtube_migrator-2.0.0.dist-info/entry_points.txt
spotify_youtube_migrator-2.0.0.dist-info/top_level.txt
spotify_youtube_migrator-2.0.0.dist-info/RECORD
