Metadata-Version: 2.4
Name: spotify-youtube-migrator
Version: 2.0.0
Summary: A Python package to migrate playlists between Spotify and YouTube Music.
Home-page: https://github.com/manojk0303/spotify-youtube-migrator
Author: Manojkumar K
Author-email: manojk030303@gmail.com
Classifier: Programming Language :: Python :: 3
Classifier: License :: OSI Approved :: MIT License
Classifier: Operating System :: OS Independent
Requires-Python: >=3.6
License-File: LICENSE
Requires-Dist: spotipy
Requires-Dist: ytmusicapi
Requires-Dist: colorama
Requires-Dist: google-auth>=2.0.0
Requires-Dist: google-auth-oauthlib>=1.0.0
Requires-Dist: google-auth-httplib2>=0.2.0
Dynamic: author
Dynamic: author-email
Dynamic: classifier
Dynamic: description
Dynamic: description-content-type
Dynamic: home-page
Dynamic: license-file
Dynamic: requires-dist
Dynamic: requires-python
Dynamic: summary
